SpringBatchCankaoWendangZhongwenban/README.md
SpringBatchCankaoWendangZhongwenban/__init__.py
SpringBatchCankaoWendangZhongwenban/__main__.py
SpringBatchCankaoWendangZhongwenban/file.epub
SpringBatchCankaoWendangZhongwenban/index.html
SpringBatchCankaoWendangZhongwenban/css/__init__.py
SpringBatchCankaoWendangZhongwenban/css/annotations.css
SpringBatchCankaoWendangZhongwenban/css/main.css
SpringBatchCankaoWendangZhongwenban/css/normalize.css
SpringBatchCankaoWendangZhongwenban/css/popup.css
SpringBatchCankaoWendangZhongwenban/font/__init__.py
SpringBatchCankaoWendangZhongwenban/font/fontello.eot
SpringBatchCankaoWendangZhongwenban/font/fontello.svg
SpringBatchCankaoWendangZhongwenban/font/fontello.ttf
SpringBatchCankaoWendangZhongwenban/font/fontello.woff
SpringBatchCankaoWendangZhongwenban/img/__init__.py
SpringBatchCankaoWendangZhongwenban/img/annotator-glyph-sprite.png
SpringBatchCankaoWendangZhongwenban/img/annotator-icon-sprite.png
SpringBatchCankaoWendangZhongwenban/img/apple-touch-icon.png
SpringBatchCankaoWendangZhongwenban/img/cancelfullscreen.png
SpringBatchCankaoWendangZhongwenban/img/close.png
SpringBatchCankaoWendangZhongwenban/img/fullscreen.png
SpringBatchCankaoWendangZhongwenban/img/loader.gif
SpringBatchCankaoWendangZhongwenban/img/menu-icon.png
SpringBatchCankaoWendangZhongwenban/img/save.png
SpringBatchCankaoWendangZhongwenban/img/saved.png
SpringBatchCankaoWendangZhongwenban/img/settings-s.png
SpringBatchCankaoWendangZhongwenban/img/settings.png
SpringBatchCankaoWendangZhongwenban/img/star.png
SpringBatchCankaoWendangZhongwenban/js/__init__.py
SpringBatchCankaoWendangZhongwenban/js/epub.js
SpringBatchCankaoWendangZhongwenban/js/epub.min.js
SpringBatchCankaoWendangZhongwenban/js/epub.min.map
SpringBatchCankaoWendangZhongwenban/js/hooks.min.js
SpringBatchCankaoWendangZhongwenban/js/hooks.min.map
SpringBatchCankaoWendangZhongwenban/js/reader.js
SpringBatchCankaoWendangZhongwenban/js/reader.js.map
SpringBatchCankaoWendangZhongwenban/js/reader.min.js
spring_batch_cankao_wendang_zhongwenban-2024.3.4.0.dist-info/METADATA
spring_batch_cankao_wendang_zhongwenban-2024.3.4.0.dist-info/WHEEL
spring_batch_cankao_wendang_zhongwenban-2024.3.4.0.dist-info/entry_points.txt
spring_batch_cankao_wendang_zhongwenban-2024.3.4.0.dist-info/top_level.txt
spring_batch_cankao_wendang_zhongwenban-2024.3.4.0.dist-info/RECORD
